inex/__init__.py
inex/engine.py
inex/helpers.py
inex/inex.py
inex/version.py
inex/version.txt
inex/utils/__init__.py
inex/utils/configure.py
inex/utils/fsystem.py
inex_launcher-3.1.3.dist-info/LICENSE
inex_launcher-3.1.3.dist-info/METADATA
inex_launcher-3.1.3.dist-info/WHEEL
inex_launcher-3.1.3.dist-info/entry_points.txt
inex_launcher-3.1.3.dist-info/top_level.txt
inex_launcher-3.1.3.dist-info/RECORD
