Metadata-Version: 2.1
Name: inex-launcher
Version: 3.1.3
Summary: InEx is a lightweight highly configurable Python launcher based on microkernel architecture
Home-page: https://github.com/speechpro/inex-launcher
Author: Yuri Khokhlov
Author-email: khokhlov@speechpro.com
License: MIT
Project-URL: Bug Tracker, https://github.com/speechpro/inex-launcher/issues
Keywords: speechpro inex launcher inex-launcher command-line configuration yaml
Classifier: License :: OSI Approved :: MIT License
Classifier: Programming Language :: Python :: 3.8
Classifier: Programming Language :: Python :: 3.9
Classifier: Programming Language :: Python :: 3.10
Classifier: Programming Language :: Python :: 3.11
Classifier: Programming Language :: Python :: 3.12
Classifier: Operating System :: POSIX :: Linux
Classifier: Operating System :: MacOS
Classifier: Operating System :: Microsoft :: Windows
Requires-Python: >=3.8
License-File: LICENSE
Requires-Dist: omegaconf
Requires-Dist: networkx
